thera_py-0.13.0.dist-info/licenses/LICENSE
therapy/__init__.py
therapy/cli.py
therapy/config.py
therapy/main.py
therapy/query.py
therapy/schemas.py
therapy/utils.py
therapy/database/__init__.py
therapy/database/database.py
therapy/database/dynamodb.py
therapy/etl/__init__.py
therapy/etl/base.py
therapy/etl/chembl.py
therapy/etl/chemidplus.py
therapy/etl/drugbank.py
therapy/etl/drugsatfda.py
therapy/etl/guidetopharmacology.py
therapy/etl/hemonc.py
therapy/etl/merge.py
therapy/etl/ncit.py
therapy/etl/rules.csv
therapy/etl/rules.py
therapy/etl/rxnorm.py
therapy/etl/update.py
therapy/etl/wikidata.py
thera_py-0.13.0.dist-info/METADATA
thera_py-0.13.0.dist-info/WHEEL
thera_py-0.13.0.dist-info/entry_points.txt
thera_py-0.13.0.dist-info/top_level.txt
thera_py-0.13.0.dist-info/RECORD
