Metadata-Version: 2.4
Name: thera-py
Version: 0.13.0
Summary: VICC normalization routines for therapeutics
Author: Alex Wagner, Kori Kuzma, James Stevenson
License-Expression: MIT
Project-URL: Homepage, https://github.com/cancervariants/therapy-normalization
Project-URL: Documentation, https://github.com/cancervariants/therapy-normalization
Project-URL: Changelog, https://github.com/cancervariants/therapy-normalization/releases
Project-URL: Source, https://github.com/cancervariants/therapy-normalization
Project-URL: Bug Tracker, https://github.com/cancervariants/therapy-normalization/issues
Classifier: Development Status :: 3 - Alpha
Classifier: Framework :: FastAPI
Classifier: Framework :: Pydantic
Classifier: Framework :: Pydantic :: 2
Classifier: Intended Audience :: Science/Research
Classifier: Intended Audience :: Developers
Classifier: Topic :: Scientific/Engineering :: Bio-Informatics
Classifier: Programming Language :: Python :: 3
Classifier: Programming Language :: Python :: 3.11
Classifier: Programming Language :: Python :: 3.12
Classifier: Programming Language :: Python :: 3.13
Requires-Python: >=3.11
License-File: LICENSE
Requires-Dist: pydantic~=2.1
Requires-Dist: pydantic-settings
Requires-Dist: fastapi
Requires-Dist: uvicorn
Requires-Dist: click
Requires-Dist: boto3
Requires-Dist: ga4gh.vrs<3.0,>=2.2.0
Requires-Dist: disease-normalizer~=0.11.0
Provides-Extra: etl
Requires-Dist: disease-normalizer[etl]~=0.11.0; extra == "etl"
Requires-Dist: owlready2; extra == "etl"
Requires-Dist: rdflib; extra == "etl"
Requires-Dist: wikibaseintegrator>=0.12.0; extra == "etl"
Requires-Dist: wags-tails~=0.4.0; extra == "etl"
Requires-Dist: tqdm; extra == "etl"
Requires-Dist: rich; extra == "etl"
Requires-Dist: pyyaml; extra == "etl"
Provides-Extra: tests
Requires-Dist: pytest>=6.0; extra == "tests"
Requires-Dist: pytest-cov; extra == "tests"
Requires-Dist: pytest-mock; extra == "tests"
Requires-Dist: httpx>=0.27.0; extra == "tests"
Requires-Dist: jsonschema~=4.24; extra == "tests"
Requires-Dist: pyyaml; extra == "tests"
Requires-Dist: asgi_lifespan; extra == "tests"
Requires-Dist: pytest_asyncio; extra == "tests"
Requires-Dist: isodate; extra == "tests"
Requires-Dist: deepdiff; extra == "tests"
Provides-Extra: dev
Requires-Dist: fastapi[standard]; extra == "dev"
Requires-Dist: prek>=0.2.23; extra == "dev"
Requires-Dist: ruff==0.14.10; extra == "dev"
Requires-Dist: lxml; extra == "dev"
Requires-Dist: xmlformatter; extra == "dev"
Requires-Dist: types-pyyaml; extra == "dev"
Dynamic: license-file
